naptools/__init__.py
naptools/contour_plot.py
naptools/contour_stream_plot.py
naptools/error_plot.py
naptools/line_styles.py
naptools/multi_plot.py
naptools/new_contour_plot.py
naptools/plot.py
naptools/plot_2d.py
naptools/stream_plot.py
naptools-0.6.1.dist-info/licenses/LICENSE
naptools-0.6.1.dist-info/METADATA
naptools-0.6.1.dist-info/WHEEL
naptools-0.6.1.dist-info/top_level.txt
naptools-0.6.1.dist-info/RECORD
