Metadata-Version: 2.4
Name: naptools
Version: 0.6.1
Summary: Python package (using matplotlib as a basis) to quickly make nice-looking numerical analysis plots.
Author-email: alextrenam <alextrenam@gmail.com>
Project-URL: Homepage, https://github.com/alextrenam/naptools
Project-URL: Issues, https://github.com/alextrenam/naptools/issues
Classifier: Programming Language :: Python :: 3
Classifier: License :: OSI Approved :: MIT License
Classifier: Operating System :: OS Independent
Requires-Python: >=3.8
License-File: LICENSE
Dynamic: license-file
